gensound/__init__.py
gensound/amplifiers.py
gensound/analyze.py
gensound/audio.py
gensound/curve.py
gensound/effects.py
gensound/filters.py
gensound/io.py
gensound/musicTheory.py
gensound/settings.py
gensound/signals.py
gensound/transforms.py
gensound/utils.py
gensound/visualise.py
gensound/data/Kushaura_sketch.wav
gensound-0.5.3.dist-info/METADATA
gensound-0.5.3.dist-info/RECORD
gensound-0.5.3.dist-info/WHEEL
gensound-0.5.3.dist-info/top_level.txt
