Metadata-Version: 2.1
Name: gensound
Version: 0.5.3
Summary: Pythonic audio processing and synthesis library
Home-page: https://github.com/Quefumas/gensound
Author: Dror Chawin
Author-email: quefumas@gmail.com
License: UNKNOWN
Platform: UNKNOWN
Requires-Dist: numpy
